{
  "meta": {
    "tool": "smbclient",
    "status": "ran"
  },
  "result": {
    "cmd": [
      "/usr/bin/smbclient",
      "https://testphp.vulnweb.com"
    ],
    "rc": 1,
    "stdout": "\nhttps:\\\\testphp.vulnweb.com: Not enough '\\' characters in service\n",
    "stderr": "Usage: smbclient [-?EgqBNPkV] [-?|--help] [--usage] [-M|--message=HOST]\n        [-I|--ip-address=IP] [-E|--stderr] [-L|--list=HOST]\n        [-T|--tar=<c|x>IXFvgbNan] [-D|--directory=DIR] [-c|--command=STRING]\n        [-b|--send-buffer=BYTES] [-t|--timeout=SECONDS] [-p|--port=PORT]\n        [-g|--grepable] [-q|--quiet] [-B|--browse]\n        [-d|--debuglevel=DEBUGLEVEL] [--debug-stdout]\n        [-s|--configfile=CONFIGFILE] [--option=name=value]\n        [-l|--log-basename=LOGFILEBASE] [--leak-report] [--leak-report-full]\n        [-R|--name-resolve=NAME-RESOLVE-ORDER]\n        [-O|--socket-options=SOCKETOPTIONS] [-m|--max-protocol=MAXPROTOCOL]\n        [-n|--netbiosname=NETBIOSNAME] [--netbios-scope=SCOPE]\n        [-W|--workgroup=WORKGROUP] [--realm=REALM]\n        [-U|--user=[DOMAIN/]USERNAME[%PASSWORD]] [-N|--no-pass]\n        [--password=STRING] [--pw-nt-hash] [-A|--authentication-file=FILE]\n        [-P|--machine-pass] [--simple-bind-dn=DN]\n        [--use-kerberos=desired|required|off] [--use-krb5-ccache=CCACHE]\n        [--use-winbind-ccache] [--client-protection=sign|encrypt|off]\n        [-k|--kerberos] [-V|--version] [OPTIONS] service <password>\n"
  },
  "parsed_findings": []
}